{"version":0,"data":[{"instancePath":"","rtlName":"entry_proc_U0","stallingFileName":"","stallingTime":"0","avgII":"104995","maxII":"104995","minII":"104995","avgLatency":"0","maxLatency":"0","minLatency":"0","stallNoStart":"0","stallNoContinue":"0","readBlockTime":"0","writeBlockTime":"0","startEndClockCycle":""},{"instancePath":"","rtlName":"Block_entry_proc_1_U0","stallingFileName":"","stallingTime":"0","avgII":"104995","maxII":"104995","minII":"104995","avgLatency":"1","maxLatency":"1","minLatency":"1","stallNoStart":"0","stallNoContinue":"0","readBlockTime":"0","writeBlockTime":"0","startEndClockCycle":""},{"instancePath":"","rtlName":"Block_entry_proc_U0","stallingFileName":"","stallingTime":"0","avgII":"104995","maxII":"104995","minII":"104995","avgLatency":"107378","maxLatency":"109779","minLatency":"104978","stallNoStart":"0","stallNoContinue":"0","readBlockTime":"0","writeBlockTime":"0","startEndClockCycle":""},{"instancePath":"","rtlName":"AESL_inst_fmm_reduce_kernel","stallingFileName":"","stallingTime":"0","avgII":"104995","maxII":"104995","minII":"104995","avgLatency":"107380","maxLatency":"109781","minLatency":"104980","stallNoStart":"0","stallNoContinue":"0","readBlockTime":"0","writeBlockTime":"0","startEndClockCycle":""},{"instancePath":"Block_entry_proc_U0","rtlName":"grp_load_matrix_from_dram_safe_fu_174","stallingFileName":"","stallingTime":"0","avgII":"104995","maxII":"104995","minII":"104995","avgLatency":"102801","maxLatency":"103120","minLatency":"102482","stallNoStart":"0","stallNoContinue":"0","readBlockTime":"0","writeBlockTime":"0","startEndClockCycle":""},{"instancePath":"Block_entry_proc_U0.grp_load_matrix_from_dram_safe_fu_174","rtlName":"grp_load_matrix_from_dram_safe_Pipeline_VITIS_LOOP_50_1_VITIS_LOOP_52_2_fu_72","stallingFileName":"","stallingTime":"0","avgII":"104995","maxII":"104995","minII":"104995","avgLatency":"102401","maxLatency":"102401","minLatency":"102401","stallNoStart":"0","stallNoContinue":"0","readBlockTime":"0","writeBlockTime":"0","startEndClockCycle":""},{"instancePath":"Block_entry_proc_U0.grp_load_matrix_from_dram_safe_fu_174","rtlName":"grp_load_matrix_from_dram_safe_Pipeline_VITIS_LOOP_59_3_VITIS_LOOP_60_4_fu_78","stallingFileName":"","stallingTime":"0","avgII":"104995","maxII":"104995","minII":"104995","avgLatency":"397","maxLatency":"716","minLatency":"78","stallNoStart":"0","stallNoContinue":"0","readBlockTime":"0","writeBlockTime":"0","startEndClockCycle":""},{"instancePath":"Block_entry_proc_U0","rtlName":"grp_greedy_potential_reduce_with_debug_fu_198","stallingFileName":"","stallingTime":"0","avgII":"105633","maxII":"105633","minII":"105633","avgLatency":"3808","maxLatency":"5269","minLatency":"2347","stallNoStart":"0","stallNoContinue":"0","readBlockTime":"0","writeBlockTime":"0","startEndClockCycle":""},{"instancePath":"Block_entry_proc_U0.grp_greedy_potential_reduce_with_debug_fu_198","rtlName":"grp_greedy_potential_reduce_with_debug_Pipeline_VITIS_LOOP_104_1_VITIS_LOOP_93_1_fu_895","stallingFileName":"","stallingTime":"0","avgII":"105633","maxII":"105633","minII":"105633","avgLatency":"283","maxLatency":"515","minLatency":"51","stallNoStart":"0","stallNoContinue":"0","readBlockTime":"0","writeBlockTime":"0","startEndClockCycle":""},{"instancePath":"Block_entry_proc_U0.grp_greedy_potential_reduce_with_debug_fu_198","rtlName":"grp_greedy_potential_reduce_with_debug_Pipeline_VITIS_LOOP_116_1_fu_904","stallingFileName":"","stallingTime":"0","avgII":"605","maxII":"103848","minII":"15","avgLatency":"24","maxLatency":"33","minLatency":"9","stallNoStart":"0","stallNoContinue":"0","readBlockTime":"0","writeBlockTime":"0","startEndClockCycle":""},{"instancePath":"Block_entry_proc_U0.grp_greedy_potential_reduce_with_debug_fu_198","rtlName":"grp_greedy_potential_reduce_with_debug_Pipeline_VITIS_LOOP_116_13_fu_915","stallingFileName":"","stallingTime":"0","avgII":"","maxII":"","minII":"","avgLatency":"8","maxLatency":"8","minLatency":"8","stallNoStart":"0","stallNoContinue":"0","readBlockTime":"0","writeBlockTime":"0","startEndClockCycle":""},{"instancePath":"Block_entry_proc_U0.grp_greedy_potential_reduce_with_debug_fu_198","rtlName":"grp_greedy_potential_reduce_with_debug_Pipeline_VITIS_LOOP_136_1_fu_925","stallingFileName":"","stallingTime":"0","avgII":"","maxII":"","minII":"","avgLatency":"24","maxLatency":"24","minLatency":"24","stallNoStart":"0","stallNoContinue":"0","readBlockTime":"0","writeBlockTime":"0","startEndClockCycle":""},{"instancePath":"Block_entry_proc_U0.grp_greedy_potential_reduce_with_debug_fu_198","rtlName":"grp_greedy_potential_reduce_with_debug_Pipeline_VITIS_LOOP_193_2_VITIS_LOOP_116_1_fu_935","stallingFileName":"","stallingTime":"0","avgII":"37","maxII":"57","minII":"17","avgLatency":"27","maxLatency":"51","minLatency":"3","stallNoStart":"0","stallNoContinue":"0","readBlockTime":"0","writeBlockTime":"0","startEndClockCycle":""},{"instancePath":"Block_entry_proc_U0.grp_greedy_potential_reduce_with_debug_fu_198","rtlName":"grp_greedy_potential_reduce_with_debug_Pipeline_VITIS_LOOP_158_1_fu_948","stallingFileName":"","stallingTime":"0","avgII":"","maxII":"","minII":"","avgLatency":"1","maxLatency":"1","minLatency":"1","stallNoStart":"0","stallNoContinue":"0","readBlockTime":"0","writeBlockTime":"0","startEndClockCycle":""},{"instancePath":"Block_entry_proc_U0.grp_greedy_potential_reduce_with_debug_fu_198","rtlName":"grp_greedy_potential_reduce_with_debug_Pipeline_VITIS_LOOP_164_2_fu_957","stallingFileName":"","stallingTime":"0","avgII":"","maxII":"","minII":"","avgLatency":"5","maxLatency":"5","minLatency":"5","stallNoStart":"0","stallNoContinue":"0","readBlockTime":"0","writeBlockTime":"0","startEndClockCycle":""},{"instancePath":"Block_entry_proc_U0.grp_greedy_potential_reduce_with_debug_fu_198","rtlName":"grp_greedy_potential_reduce_with_debug_Pipeline_VITIS_LOOP_175_3_fu_968","stallingFileName":"","stallingTime":"0","avgII":"","maxII":"","minII":"","avgLatency":"17","maxLatency":"17","minLatency":"17","stallNoStart":"0","stallNoContinue":"0","readBlockTime":"0","writeBlockTime":"0","startEndClockCycle":""},{"instancePath":"Block_entry_proc_U0.grp_greedy_potential_reduce_with_debug_fu_198","rtlName":"grp_greedy_potential_reduce_with_debug_Pipeline_VITIS_LOOP_116_14_fu_979","stallingFileName":"","stallingTime":"0","avgII":"700","maxII":"700","minII":"700","avgLatency":"9","maxLatency":"9","minLatency":"9","stallNoStart":"0","stallNoContinue":"0","readBlockTime":"0","writeBlockTime":"0","startEndClockCycle":""},{"instancePath":"Block_entry_proc_U0.grp_greedy_potential_reduce_with_debug_fu_198","rtlName":"grp_greedy_potential_reduce_with_debug_Pipeline_VITIS_LOOP_136_15_fu_989","stallingFileName":"","stallingTime":"0","avgII":"700","maxII":"700","minII":"700","avgLatency":"27","maxLatency":"29","minLatency":"26","stallNoStart":"0","stallNoContinue":"0","readBlockTime":"0","writeBlockTime":"0","startEndClockCycle":""},{"instancePath":"Block_entry_proc_U0.grp_greedy_potential_reduce_with_debug_fu_198","rtlName":"grp_greedy_potential_reduce_with_debug_Pipeline_VITIS_LOOP_193_2_VITIS_LOOP_116_16_fu_999","stallingFileName":"","stallingTime":"0","avgII":"70","maxII":"481","minII":"17","avgLatency":"29","maxLatency":"59","minLatency":"3","stallNoStart":"0","stallNoContinue":"0","readBlockTime":"0","writeBlockTime":"0","startEndClockCycle":""},{"instancePath":"Block_entry_proc_U0.grp_greedy_potential_reduce_with_debug_fu_198","rtlName":"grp_greedy_potential_reduce_with_debug_Pipeline_VITIS_LOOP_158_17_fu_1012","stallingFileName":"","stallingTime":"0","avgII":"768","maxII":"768","minII":"768","avgLatency":"5","maxLatency":"5","minLatency":"5","stallNoStart":"0","stallNoContinue":"0","readBlockTime":"0","writeBlockTime":"0","startEndClockCycle":""},{"instancePath":"Block_entry_proc_U0.grp_greedy_potential_reduce_with_debug_fu_198","rtlName":"grp_greedy_potential_reduce_with_debug_Pipeline_VITIS_LOOP_164_28_fu_1021","stallingFileName":"","stallingTime":"0","avgII":"768","maxII":"768","minII":"768","avgLatency":"3","maxLatency":"4","minLatency":"3","stallNoStart":"0","stallNoContinue":"0","readBlockTime":"0","writeBlockTime":"0","startEndClockCycle":""},{"instancePath":"Block_entry_proc_U0.grp_greedy_potential_reduce_with_debug_fu_198","rtlName":"grp_greedy_potential_reduce_with_debug_Pipeline_VITIS_LOOP_175_39_fu_1032","stallingFileName":"","stallingTime":"0","avgII":"769","maxII":"769","minII":"769","avgLatency":"18","maxLatency":"19","minLatency":"17","stallNoStart":"0","stallNoContinue":"0","readBlockTime":"0","writeBlockTime":"0","startEndClockCycle":""},{"instancePath":"Block_entry_proc_U0.grp_greedy_potential_reduce_with_debug_fu_198","rtlName":"grp_greedy_potential_reduce_with_debug_Pipeline_VITIS_LOOP_136_110_fu_1043","stallingFileName":"","stallingTime":"0","avgII":"834","maxII":"834","minII":"834","avgLatency":"27","maxLatency":"29","minLatency":"26","stallNoStart":"0","stallNoContinue":"0","readBlockTime":"0","writeBlockTime":"0","startEndClockCycle":""},{"instancePath":"Block_entry_proc_U0.grp_greedy_potential_reduce_with_debug_fu_198","rtlName":"grp_greedy_potential_reduce_with_debug_Pipeline_VITIS_LOOP_104_1_VITIS_LOOP_93_111_fu_1055","stallingFileName":"","stallingTime":"0","avgII":"837","maxII":"837","minII":"837","avgLatency":"74","maxLatency":"83","minLatency":"66","stallNoStart":"0","stallNoContinue":"0","readBlockTime":"0","writeBlockTime":"0","startEndClockCycle":""},{"instancePath":"Block_entry_proc_U0","rtlName":"grp_store_matrix_to_dram_safe_fu_218","stallingFileName":"","stallingTime":"0","avgII":"108555","maxII":"108555","minII":"108555","avgLatency":"763","maxLatency":"1384","minLatency":"143","stallNoStart":"0","stallNoContinue":"0","readBlockTime":"0","writeBlockTime":"0","startEndClockCycle":""},{"instancePath":"Block_entry_proc_U0.grp_store_matrix_to_dram_safe_fu_218","rtlName":"grp_store_matrix_to_dram_safe_Pipeline_VITIS_LOOP_77_1_VITIS_LOOP_78_2_fu_40","stallingFileName":"","stallingTime":"0","avgII":"108555","maxII":"108555","minII":"108555","avgLatency":"760","maxLatency":"1381","minLatency":"140","stallNoStart":"0","stallNoContinue":"0","readBlockTime":"0","writeBlockTime":"0","startEndClockCycle":""}]}
